local_faiss_mcp/__init__.py
local_faiss_mcp/__main__.py
local_faiss_mcp/cli.py
local_faiss_mcp/document_parser.py
local_faiss_mcp/server.py
local_faiss_mcp-0.2.0.dist-info/licenses/LICENSE
local_faiss_mcp-0.2.0.dist-info/METADATA
local_faiss_mcp-0.2.0.dist-info/WHEEL
local_faiss_mcp-0.2.0.dist-info/entry_points.txt
local_faiss_mcp-0.2.0.dist-info/top_level.txt
local_faiss_mcp-0.2.0.dist-info/RECORD
