Metadata-Version: 2.4
Name: local-faiss-mcp
Version: 0.2.0
Summary: MCP server with FAISS local vector database for RAG
Author-email: Fabio Nonato <nonatofabio@gmail.com>
License-Expression: MIT
Project-URL: Homepage, https://github.com/nonatofabio/local_faiss_mcp
Project-URL: Repository, https://github.com/nonatofabio/local_faiss_mcp
Project-URL: Issues, https://github.com/nonatofabio/local_faiss_mcp/issues
Keywords: mcp,faiss,rag,vector-database,semantic-search,embeddings,ai
Classifier: Development Status :: 4 - Beta
Classifier: Intended Audience :: Developers
Classifier: Programming Language :: Python :: 3
Classifier: Programming Language :: Python :: 3.10
Classifier: Programming Language :: Python :: 3.11
Classifier: Programming Language :: Python :: 3.12
Classifier: Topic :: Scientific/Engineering :: Artificial Intelligence
Classifier: Topic :: Software Development :: Libraries :: Python Modules
Requires-Python: >=3.10
License-File: LICENSE
Requires-Dist: mcp>=0.9.0
Requires-Dist: faiss-cpu>=1.8.0
Requires-Dist: sentence-transformers>=2.2.0
Requires-Dist: numpy>=1.24.0
Requires-Dist: pypdf>=4.0.0
Provides-Extra: dev
Requires-Dist: pytest>=7.0.0; extra == "dev"
Requires-Dist: pytest-asyncio>=0.21.0; extra == "dev"
Requires-Dist: build>=1.0.0; extra == "dev"
Requires-Dist: twine>=4.0.0; extra == "dev"
Dynamic: license-file
